fakewsserver/__init__.py
fakewsserver/_server.py
fakewsserver-0.2.1.dist-info/LICENSE
fakewsserver-0.2.1.dist-info/WHEEL
fakewsserver-0.2.1.dist-info/METADATA
fakewsserver-0.2.1.dist-info/RECORD
