Metadata-Version: 2.1
Name: fakewsserver
Version: 0.2.1
Summary: Websocket server for testing
Author: uigctaw
Author-email: uigctaw@protonmail.com
Requires-Python: >=3.9,<4.0
Classifier: Programming Language :: Python :: 3
Classifier: Programming Language :: Python :: 3.9
Requires-Dist: websockets (>=9.1,<10.0)
